context_server/__init__.py
context_server/main.py
context_local_server-0.1.1.dist-info/METADATA
context_local_server-0.1.1.dist-info/WHEEL
context_local_server-0.1.1.dist-info/entry_points.txt
context_local_server-0.1.1.dist-info/top_level.txt
context_local_server-0.1.1.dist-info/RECORD
