Metadata-Version: 2.4
Name: context-local-server
Version: 0.1.1
Summary: A stdio MCP server to provide long-term memory for AI agents.
Author-email: David Marcas Luna <david.marcas@gmail.com>
License: MIT License
Requires-Python: >=3.8
Requires-Dist: fastmcp
Requires-Dist: pydantic
